LICENSE
README.md
setup.py
discord/ext/vector/__init__.py
discord/ext/vector/main.py
discord_ext_vector.egg-info/PKG-INFO
discord_ext_vector.egg-info/SOURCES.txt
discord_ext_vector.egg-info/dependency_links.txt
discord_ext_vector.egg-info/requires.txt
discord_ext_vector.egg-info/top_level.txt